finitelycomputable/flask_dispatcher.py
finitelycomputable/tests/test_flask_dispatcher.py
finitelycomputable_flask_dispatcher-25.7.dist-info/METADATA
finitelycomputable_flask_dispatcher-25.7.dist-info/WHEEL
finitelycomputable_flask_dispatcher-25.7.dist-info/entry_points.txt
finitelycomputable_flask_dispatcher-25.7.dist-info/top_level.txt
finitelycomputable_flask_dispatcher-25.7.dist-info/RECORD
